databricks_openai/__init__.py
databricks_openai/mcp_server_toolkit.py
databricks_openai/vector_search_retriever_tool.py
databricks_openai/agents/__init__.py
databricks_openai/agents/mcp_server.py
databricks_openai/uc_ai/__init__.py
databricks_openai/utils/clients.py
databricks_openai-0.8.0.dist-info/METADATA
databricks_openai-0.8.0.dist-info/WHEEL
databricks_openai-0.8.0.dist-info/RECORD
