Metadata-Version: 2.4
Name: databricks-openai
Version: 0.8.0
Summary: Support for Databricks AI support with OpenAI
Author-email: Databricks <agent-feedback@databricks.com>
License: Apache-2.0
Requires-Python: >=3.10
Requires-Dist: databricks-ai-bridge>=0.4.2
Requires-Dist: databricks-mcp>=0.4.0
Requires-Dist: databricks-vectorsearch>=0.50
Requires-Dist: langchain>=0.3.0
Requires-Dist: mlflow>=2.20.1
Requires-Dist: openai-agents>=0.5.0
Requires-Dist: openai>=1.99.9
Requires-Dist: pydantic>2.10.0
Requires-Dist: unitycatalog-openai[databricks]>=0.2.0
Provides-Extra: dev
Requires-Dist: databricks-sdk>=0.34.0; extra == 'dev'
Requires-Dist: pytest; extra == 'dev'
Requires-Dist: pytest-asyncio; extra == 'dev'
Requires-Dist: ruff==0.6.4; extra == 'dev'
Requires-Dist: typing-extensions; extra == 'dev'
Provides-Extra: integration
Requires-Dist: pytest-timeout>=2.3.1; extra == 'integration'
